mirrorstr/__init__.py
mirrorstr/mirrorstr.py
mirrorstr/mp4_to_gif.py
mirrorstr/post_note.py
mirrorstr/relay_list.txt
mirrorstr/upload_to_voidcat_and_return_url.py
Mirrorstr-0.0.81.dist-info/LICENSE
Mirrorstr-0.0.81.dist-info/METADATA
Mirrorstr-0.0.81.dist-info/WHEEL
Mirrorstr-0.0.81.dist-info/entry_points.txt
Mirrorstr-0.0.81.dist-info/top_level.txt
Mirrorstr-0.0.81.dist-info/RECORD
