Metadata-Version: 2.1
Name: Mirrorstr
Version: 0.0.81
Summary: An application to mirror Nostr posts on twitter, and vice-versa
Author-email: pleblira <pleblira@gmail.com>
Project-URL: Homepage, https://github.com/pleblira/mirrorstr
Project-URL: Bug Tracker, https://github.com/pleblira/mirrorstr/issues
Classifier: Programming Language :: Python :: 3
Classifier: License :: OSI Approved :: MIT License
Classifier: Operating System :: OS Independent
Requires-Python: >=3.7
License-File: LICENSE
Requires-Dist: moviepy (==1.0.3)
Requires-Dist: nostr (==0.0.2)
Requires-Dist: numpy (==1.24.3)
Requires-Dist: Pillow (==9.5.0)
Requires-Dist: Requests (==2.31.0)
Requires-Dist: APScheduler (==3.10.1)
